{
  "main": [
    {
      "name": "Home",
      "url": "/"
    },
    {
      "name": "Documentation",
      "url": "/linux/"
    },
    {
      "name": "Reference",
      "url": "",
      "hasChildren": true,
      "children": [
        {
          "name": "Linux",
          "url": "/linux/linux-introduction/"
        },
        {
          "name": "Privacy",
          "url": "/privacy/intro-privacy"
        }
      ]
    }
  ],
  "footer": {
    "community": {
      "title": "Join Our Community",
      "links": [
				{
					"name": "Telegram",
					"url": "https://t.me/The_PenguinsClub"
				},
        {
          "name": "GitHub",
          "url": "https://github.com/The-Penguins-Club"
        },
        {
          "name": "Discord Community",
          "url": "/"
        },
        {
          "name": "Twitter Updates",
          "url": "https://x.com/OrgPenguins"
        }
      ]
    },
    "help_links": {
      "title": "Helpful Links",
      "links": [
        {
          "name": "Getting Started",
          "url": "/"
        },
        {
          "name": "Privacy Policy",
          "url": "/privacy-policy"
        },
        {
          "name": "Terms and Conditions",
          "url": "/terms-conditions"
        },
        {
          "name": "About Us",
          "url": "/about"
        }
      ]
    },
    "company": {
      "title": "Resources",
      "links": [
        {
          "name": "Linux",
          "url": "/linux/"
        },
        {
          "name": "Security",
          "url": "/security/"
        },
        {
          "name": "Privacy",
          "url": "/privacy/"
        },
        {
          "name": "FOSS",
          "url": "/foss/"
        }
      ]
    }
  }
}
